harbory/__init__.py
harbory/__main__.py
harbory/commands/__init__.py
harbory/commands/machinery.py
harbory/commands/subcommand.py
harbory/commands/workflow.py
harbory/common/astutils.py
harbory/common/base58.py
harbory/common/dag.py
harbory/common/git.py
harbory/common/hashutils.py
harbory/common/iterutils.py
harbory/common/jsonnet.py
harbory/common/logutils.py
harbory/common/pkgutils.py
harbory/common/typeutils.py
harbory/constants.py
harbory/integrations/__init__.py
harbory/integrations/mlflow/__init__.py
harbory/integrations/mlflow/constants.py
harbory/integrations/mlflow/utils.py
harbory/integrations/mlflow/workflow.py
harbory/machinery/__init__.py
harbory/machinery/archive.py
harbory/machinery/colt.py
harbory/machinery/data.py
harbory/machinery/format.py
harbory/machinery/model.py
harbory/machinery/processor.py
harbory/machinery/settings.py
harbory/machinery/step.py
harbory/machinery/types.py
harbory/machinery/utils.py
harbory/py.typed
harbory/settings.py
harbory/types.py
harbory/workflow/__init__.py
harbory/workflow/cache.py
harbory/workflow/callback.py
harbory/workflow/colt.py
harbory/workflow/constants.py
harbory/workflow/executor.py
harbory/workflow/format.py
harbory/workflow/graph.py
harbory/workflow/organizer.py
harbory/workflow/settings.py
harbory/workflow/step.py
harbory/workflow/types.py
harbory/workflow/utils.py
harbory-0.0.10.dist-info/LICENSE
harbory-0.0.10.dist-info/METADATA
harbory-0.0.10.dist-info/WHEEL
harbory-0.0.10.dist-info/entry_points.txt
harbory-0.0.10.dist-info/RECORD
